not_tf_opt/__init__.py
not_tf_opt/optimize.py
not_tf_opt/variables.py
tests/__init__.py
tests/test_optimize.py
tests/test_variables.py
tests/utils.py
not_tf_opt-0.0.3.dist-info/LICENSE
not_tf_opt-0.0.3.dist-info/METADATA
not_tf_opt-0.0.3.dist-info/WHEEL
not_tf_opt-0.0.3.dist-info/top_level.txt
not_tf_opt-0.0.3.dist-info/RECORD
