Metadata-Version: 2.1
Name: not-tf-opt
Version: 0.0.3
Summary: A package that provides a nicer interface to various TF 2.0 optimizers.
Home-page: https://github.com/gergely-flamich/not-tf-opt
Author: Gergely Flamich
Author-email: flamich.gergely@gmail.com
License: UNKNOWN
Platform: UNKNOWN
Classifier: Programming Language :: Python :: 3
Classifier: License :: OSI Approved :: MIT License
Classifier: Operating System :: OS Independent
Requires-Python: >=3.6
Requires-Dist: tensorflow-probability
